python_custom_exceptions/__init__.py
python_custom_exceptions/base_custom_exception.py
python_custom_exceptions/connection_exceptions.py
python_custom_exceptions/is_exist_exception.py
python_custom_exceptions-0.0.2.dist-info/licenses/LICENSE
python_custom_exceptions-0.0.2.dist-info/METADATA
python_custom_exceptions-0.0.2.dist-info/WHEEL
python_custom_exceptions-0.0.2.dist-info/top_level.txt
python_custom_exceptions-0.0.2.dist-info/RECORD
