Metadata-Version: 2.4
Name: python-custom-exceptions
Version: 0.0.2
Summary: A collection of custom exceptions for Python projects.
Home-page: https://github.com/aviz92/python-custom-exceptions
Author: Avi Zaguri
Author-email: 
Project-URL: Repository, https://github.com/aviz92/python-custom-exceptions
Requires-Python: >=3.11
License-File: LICENSE
Requires-Dist: setuptools
Requires-Dist: wheel
Requires-Dist: python-dotenv
Requires-Dist: pre-commit
Requires-Dist: colorlog
Requires-Dist: pytest
Requires-Dist: pathlib
Requires-Dist: pytest-plugins
Requires-Dist: custom-python-logger
Requires-Dist: python-base-toolkit
Dynamic: author
Dynamic: description
Dynamic: description-content-type
Dynamic: home-page
Dynamic: license-file
Dynamic: project-url
Dynamic: requires-dist
Dynamic: requires-python
Dynamic: summary
